HintlyDataAnalisys/DataAnalisys.py
HintlyDataAnalisys/__init__.py
HintlyDataAnalisys/matchmaker.json
HintlyDataAnalisys/plugins/timeLib.py
HintlyDataAnalisys-0.4.2.4.dist-info/LICENSE
HintlyDataAnalisys-0.4.2.4.dist-info/METADATA
HintlyDataAnalisys-0.4.2.4.dist-info/WHEEL
HintlyDataAnalisys-0.4.2.4.dist-info/top_level.txt
HintlyDataAnalisys-0.4.2.4.dist-info/RECORD
