Metadata-Version: 2.1
Name: HintlyDataAnalisys
Version: 0.4.2.4
Summary: Library for mathematical, financial and textual analysis
Home-page: 
Author: Franciszek Chmielewski
Author-email: ferko2610@gmail.com
Keywords: mathematics analysis text data ai
Classifier: Programming Language :: Python :: 3
Classifier: License :: OSI Approved :: MIT License
Classifier: Operating System :: OS Independent
Requires-Python: >=3.6
License-File: LICENSE
